daltools/__init__.py
daltools/basinfo.py
daltools/dens.py
daltools/ggadiff.py
daltools/ggakey.py
daltools/huckel.py
daltools/linalg.py
daltools/lr.py
daltools/mol.py
daltools/one.py
daltools/prop.py
daltools/qr.py
daltools/rspvec.py
daltools/sirifc.py
daltools/sirrst.py
daltools-1.1.8.dist-info/licenses/LICENSE
daltools-1.1.8.dist-info/METADATA
daltools-1.1.8.dist-info/WHEEL
daltools-1.1.8.dist-info/top_level.txt
daltools-1.1.8.dist-info/RECORD
