Metadata-Version: 2.4
Name: daltools
Version: 1.1.8
Summary: Daltools: utilities for extracting data from Dalton quantum chemistry calculations
Home-page: https://github.com/vahtras/daltools
Author: Olav Vahtras
Author-email: olav.vahtras@gmail.com
License: GPLv3
Classifier: Development Status :: 5 - Production/Stable
Classifier: Intended Audience :: Science/Research
Classifier: License :: OSI Approved :: GNU General Public License v3 (GPLv3)
Classifier: Programming Language :: Python
Classifier: Programming Language :: Python :: 3
Classifier: Programming Language :: Python :: 3.9
Classifier: Topic :: Scientific/Engineering :: Chemistry
License-File: LICENSE
Requires-Dist: blocked-matrix-utils>=1.0.9
Requires-Dist: fortran-binary
Dynamic: license-file
